{
  "video_id": "EiKNfIAqHb0",
  "title": "Mamalia vs Reptil: Apa yang Membedakan Penglihatan Mereka?",
  "topic": "fakta-tentang-penglihatan-mamalia-vs-reptil",
  "channel": "konten-1",
  "ts": "20260714_075437",
  "article": {
    "title": "Mamalia vs Reptil: Mengungkap Perbedaan Penglihatan yang Luar Biasa",
    "content": "<p>Mamalia dan reptil terkadang dapat terlihat memiliki banyak kesamaan, tetapi beberapa perbedaan mencolok antara keduanya terletak pada aspek penglihatan. Sejak lama, para ilmuwan telah penasaran tentang bagaimana kedua kelompok hewan ini mengalami dunia visual. Penglihatan adalah salah satu indra yang paling penting bagi sebagian besar hewan, memungkinkan mereka untuk berinteraksi dengan lingkungan, mencari makan, dan menghindari predator.</p>\n   <p>Salah satu perbedaan utama antara penglihatan mamalia dan reptil adalah struktur mata. Pada mamalia, mata memiliki lensa yang fleksibel yang dapat berubah bentuk untuk fokus pada objek yang berbeda-beda jaraknya. Sementara itu, reptil memiliki lensa yang kurang fleksibel, sehingga mereka lebih sulit untuk fokus pada objek yang bergerak atau berjarak. Selain itu, mata reptil juga memiliki koroid yang lebih tebal, yaitu lapisan berpigmen yang membantu mengurangi pantulan cahaya di dalam mata.</p>\n   <p>Perbedaan lainnya adalah distribusi konus dan batang pada retina mata. Pada mamalia, konus yang sensitif terhadap warna memungkinkan penglihatan berwarna, sedangkan batang lebih sensitif terhadap cahaya dan memungkinkan penglihatan hitam-putih. Pada reptil, jenis sel-sel retina ini juga ada, namun distribusinya berbeda-beda antara spesies. Beberapa reptil memiliki penglihatan berwarna yang sangat baik, sementara yang lain memiliki penglihatan yang lebih adaptif untuk kondisi cahaya redup.</p>\n   <p>Fakta menarik tentang reptil adalah beberapa spesiesnya memiliki kemampuan untuk melihat dalam spektrum ultraviolet (UV), yang tidak dapat dilihat oleh mamalia. Ini sangat berguna untuk mencari makan, navigasi, dan komunikasi. Beberapa spesies reptil, seperti kadal, juga dapat melihat ke arah belakang tanpa harus memutar kepala mereka, berkat posisi mata yang dapat bergerak secara independen.</p>\n   <p>Mengingat perbedaan-perbedaan ini, kedua kelompok hewan ini telah berkembang dengan cara yang unik untuk beradaptasi dengan lingkungan mereka. Mamalia, dengan kemampuan penglihatan yang sangat baik dalam kondisi cahaya normal, seringnya aktif pada siang hari. Sementara itu, reptil, yang lebih banyak mengandalkan indra lain seperti penglihatan malam atau pendengaran, aktif pada berbagai waktu, tergantung pada spesies dan lingkungan mereka.</p>\n   <p>Untuk kesimpulan, perbedaan penglihatan antara mamalia dan reptil adalah hasil evolusi yang memungkinkan kedua kelompok ini untuk hidup dan berkembang dalam beragam lingkungan. Mengerti perbedaan ini tidak hanya memberikan wawasan tentang keanekaragaman hayati, tetapi juga mengingatkan kita betapa pentingnya menghargai dan melindungi kehidupan hewan di bumi.</p>"
  },
  "slug": "mamalia-vs-reptil-mengungkap-perbedaan-penglihatan-yang-luar"
}